regression_single_target/__init__.py
regression_single_target/regression_single_target.py
Regression_single_target-0.1.dist-info/LICENSE
Regression_single_target-0.1.dist-info/METADATA
Regression_single_target-0.1.dist-info/WHEEL
Regression_single_target-0.1.dist-info/top_level.txt
Regression_single_target-0.1.dist-info/RECORD
